{
  "type": "FeatureCollection",
  "features": [
    {
      "type": "Feature",
      "properties": {},
      "geometry": {
        "type": "Polygon",
        "coordinates": [
          [
            [
              -0.11930465698242188,
              51.518290392174535
            ],
            [
              -0.1073312759399414,
              51.518290392174535
            ],
            [
              -0.1073312759399414,
              51.52472577186193
            ],
            [
              -0.11930465698242188,
              51.52472577186193
            ],
            [
              -0.11930465698242188,
              51.518290392174535
            ]
          ]
        ]
      }
    }
  ]
}